LICENSE
MANIFEST.in
README.md
requirements.txt
setup.py
bot_ci/__init__.py
bot_ci/__main__.py
bot_ci/utilities.py
telegram_bot_deploy.egg-info/PKG-INFO
telegram_bot_deploy.egg-info/SOURCES.txt
telegram_bot_deploy.egg-info/dependency_links.txt
telegram_bot_deploy.egg-info/entry_points.txt
telegram_bot_deploy.egg-info/requires.txt
telegram_bot_deploy.egg-info/top_level.txt