Metadata-Version: 2.1
Name: telegram-bot-deploy
Version: 0.2.1
Summary: telegram-bot-deploy is a simple script that perform continuous deployment for a Telegram bot.
Home-page: https://github.com/ciotto/telegram-bot-deploy
Author: Christian Bianciotto
Author-email: info@ci8.it
License: MIT
Download-URL: https://github.com/ciotto/telegram-bot-deploy/archive/v0.2.1.tar.gz
Keywords: telegram,bot,CI,CD,release
Platform: UNKNOWN
Classifier: Development Status :: 4 - Beta
Classifier: Intended Audience :: Developers
Classifier: License :: OSI Approved :: MIT License
Classifier: Natural Language :: English
Classifier: Operating System :: OS Independent
Classifier: Programming Language :: Python :: 2
Classifier: Programming Language :: Python :: 2.7
Classifier: Programming Language :: Python :: 3
Classifier: Programming Language :: Python :: 3.4
Classifier: Programming Language :: Python :: 3.5
Classifier: Programming Language :: Python :: 3.6
Classifier: Programming Language :: Python :: 3.7
Classifier: Programming Language :: Python :: 3.8
Classifier: Programming Language :: Python :: Implementation :: PyPy
Classifier: Topic :: Software Development :: Build Tools
